odoo8_addon_account_statement_operation_multicompany-8.0.0.2.0.99.dev16-py2.7-nspkg.pth
odoo8_addon_account_statement_operation_multicompany-8.0.0.2.0.99.dev16.dist-info/METADATA
odoo8_addon_account_statement_operation_multicompany-8.0.0.2.0.99.dev16.dist-info/RECORD
odoo8_addon_account_statement_operation_multicompany-8.0.0.2.0.99.dev16.dist-info/WHEEL
odoo8_addon_account_statement_operation_multicompany-8.0.0.2.0.99.dev16.dist-info/namespace_packages.txt
odoo8_addon_account_statement_operation_multicompany-8.0.0.2.0.99.dev16.dist-info/top_level.txt
odoo_addons/account_statement_operation_multicompany/README.rst
odoo_addons/account_statement_operation_multicompany/__init__.py
odoo_addons/account_statement_operation_multicompany/__openerp__.py
odoo_addons/account_statement_operation_multicompany/account.py
odoo_addons/account_statement_operation_multicompany/account_view.xml
odoo_addons/account_statement_operation_multicompany/i18n/account_statement_operation_multicompany.pot
odoo_addons/account_statement_operation_multicompany/i18n/ar.po
odoo_addons/account_statement_operation_multicompany/i18n/bg.po
odoo_addons/account_statement_operation_multicompany/i18n/bs.po
odoo_addons/account_statement_operation_multicompany/i18n/ca.po
odoo_addons/account_statement_operation_multicompany/i18n/ca_ES.po
odoo_addons/account_statement_operation_multicompany/i18n/cs.po
odoo_addons/account_statement_operation_multicompany/i18n/da.po
odoo_addons/account_statement_operation_multicompany/i18n/de.po
odoo_addons/account_statement_operation_multicompany/i18n/el_GR.po
odoo_addons/account_statement_operation_multicompany/i18n/en_GB.po
odoo_addons/account_statement_operation_multicompany/i18n/es.po
odoo_addons/account_statement_operation_multicompany/i18n/es_CR.po
odoo_addons/account_statement_operation_multicompany/i18n/es_EC.po
odoo_addons/account_statement_operation_multicompany/i18n/es_ES.po
odoo_addons/account_statement_operation_multicompany/i18n/es_MX.po
odoo_addons/account_statement_operation_multicompany/i18n/et.po
odoo_addons/account_statement_operation_multicompany/i18n/fi.po
odoo_addons/account_statement_operation_multicompany/i18n/fr.po
odoo_addons/account_statement_operation_multicompany/i18n/gl.po
odoo_addons/account_statement_operation_multicompany/i18n/hr.po
odoo_addons/account_statement_operation_multicompany/i18n/hr_HR.po
odoo_addons/account_statement_operation_multicompany/i18n/hu.po
